LICENSE
MANIFEST.in
README.md
setup.py
ahrefs_api_python/__init__.py
ahrefs_api_python/api.py
ahrefs_api_python.egg-info/PKG-INFO
ahrefs_api_python.egg-info/SOURCES.txt
ahrefs_api_python.egg-info/dependency_links.txt
ahrefs_api_python.egg-info/top_level.txt